program/__init__.py
program/split.py
ProSplit-0.0.1.dist-info/METADATA
ProSplit-0.0.1.dist-info/WHEEL
ProSplit-0.0.1.dist-info/top_level.txt
ProSplit-0.0.1.dist-info/RECORD
